apollo_pydantic/__init__.py
apollo_pydantic/client.py
apollo_pydantic/core.py
apollo_pydantic/logger.py
apollo_pydantic-0.0.3.dist-info/licenses/LICENSE
apollo_pydantic-0.0.3.dist-info/METADATA
apollo_pydantic-0.0.3.dist-info/WHEEL
apollo_pydantic-0.0.3.dist-info/top_level.txt
apollo_pydantic-0.0.3.dist-info/RECORD
