Metadata-Version: 2.4
Name: apollo_pydantic
Version: 0.0.3
Summary: apollo client wrapped by pydantic
Author-email: ryanrain2016 <holidaylover2010@gmail.com>
Project-URL: Homepage, https://github.com/ryanrain2016/apollo_pydantic
Project-URL: Issues, https://github.com/ryanrain2016/apollo_pydantic/issues
Keywords: pydantic,apollo,config,distributed,configuration,settings,microservice
Classifier: Programming Language :: Python :: 3
Classifier: Intended Audience :: Developers
Classifier: License :: OSI Approved :: MIT License
Classifier: Operating System :: OS Independent
Requires-Python: >=3.10
License-File: LICENSE
Requires-Dist: httpx>=0.27.0
Requires-Dist: pydantic-settings<3.0.0,>=2.0.0
Dynamic: license-file
